{
  "title": "Spider's Castle White Silk",
  "description": "One day, the spider Metallica wouldn’t eat any of its meal of flesh and blood. Delegated by her senpai, Machala has to clean up after Matallica in addition to making sure it eats, even if it means her death. Will Metallica eat their food? Will Machala come back in one piece?",
  "artist": "Kouhei Shibata",
  "author": "Kouhei Shibata",
  "cover": "https://cdn.imgchest.com/files/91e5c4c06d6e.jpg",
  "chapters": {
    "1": {
      "title": "One-Shot",
      "volume": "",
      "last_updated": "1758835553",
      "groups": {
        "Send Us Pictures of Anime Girls Eating Hamburgers": "/proxy/api/imgchest/chapter/bp45qwdrn45"
      }
    }
  }
}